README
setup.py
src/mockldap/__init__.py
src/mockldap/ldapobject.py
src/mockldap/recording.py
src/mockldap/tests.py
src/mockldap_fork.egg-info/PKG-INFO
src/mockldap_fork.egg-info/SOURCES.txt
src/mockldap_fork.egg-info/dependency_links.txt
src/mockldap_fork.egg-info/requires.txt
src/mockldap_fork.egg-info/top_level.txt