Metadata-Version: 1.1
Name: mockldap-fork
Version: 0.1.6
Summary: Mockldap fork, A simple mock implementation of python-ldap.
Home-page: http://bitbucket.org/psagers/mockldap/
Author: Peter Sagerson
Author-email: psagers.pypi@ignorare.net
License: BSD
Keywords: mock,ldap
Platform: UNKNOWN
Classifier: Development Status :: 2 - Pre-Alpha
Classifier: Environment :: Web Environment
Classifier: Programming Language :: Python
Classifier: Framework :: Django
Classifier: Intended Audience :: Developers
Classifier: Intended Audience :: System Administrators
Classifier: License :: OSI Approved :: BSD License
Classifier: Topic :: Internet :: WWW/HTTP
Classifier: Topic :: System :: Systems Administration :: Authentication/Directory :: LDAP
Classifier: Topic :: Software Development :: Libraries :: Python Modules
